convlog_rs-0.3.0.dist-info/METADATA
convlog_rs-0.3.0.dist-info/WHEEL
convlog_rs-0.3.0.dist-info/licenses/LICENSE
convlog_rs.libs/libgcc_s-1e52349c.so.1
convlog_rs/_convlog.pyi
convlog_rs/__init__.py
convlog_rs/py.typed
convlog_rs/_convlog.cpython-312-x86_64-linux-musl.so
convlog_rs-0.3.0.dist-info/RECORD
